euvd/__init__.py
euvd/clients/__init__.py
euvd/clients/_baseclient.py
euvd/clients/euvdasyncclient.py
euvd/clients/euvdsyncclient.py
euvd/exceptions/__init__.py
euvd/exceptions/euvdexception.py
euvd/exceptions/euvdnotfoundexception.py
euvd/models/__init__.py
euvd/models/_baseenisaidreference.py
euvd/models/_baserecord.py
euvd/models/_basevulnerability.py
euvd/models/advisory.py
euvd/models/basescore.py
euvd/models/customfieldtypes.py
euvd/models/enisaidenisavulnerabilityref.py
euvd/models/enisaidproductref.py
euvd/models/enisaidvendorref.py
euvd/models/enisaidvulnerabilityref.py
euvd/models/enisavulnerability.py
euvd/models/pagination.py
euvd/models/product.py
euvd/models/source.py
euvd/models/vendor.py
euvd/models/vulnerability.py
euvd-1.0.0b2.dist-info/METADATA
euvd-1.0.0b2.dist-info/WHEEL
euvd-1.0.0b2.dist-info/RECORD
