Metadata-Version: 2.4
Name: euvd
Version: 1.0.0b2
Author: Jesús Alonso Abad
License-Expression: MIT
Classifier: Development Status :: 4 - Beta
Classifier: Intended Audience :: Information Technology
Classifier: License :: OSI Approved :: MIT License
Classifier: Natural Language :: English
Classifier: Operating System :: OS Independent
Classifier: Programming Language :: Python :: 3
Classifier: Programming Language :: Python :: 3 :: Only
Classifier: Programming Language :: Python :: 3.11
Classifier: Programming Language :: Python :: 3.12
Classifier: Programming Language :: Python :: 3.13
Classifier: Programming Language :: Python :: 3.14
Classifier: Topic :: Security
Classifier: Topic :: Software Development :: Libraries
Classifier: Topic :: Software Development :: Libraries :: Python Modules
Classifier: Typing :: Typed
Requires-Python: >=3.11
Requires-Dist: cvss~=3.4
Requires-Dist: httpx~=0.28
Requires-Dist: pydantic~=2.11
Provides-Extra: test
Requires-Dist: mypy~=1.8; extra == 'test'
Requires-Dist: pylint~=3.0; extra == 'test'
Requires-Dist: pytest-asyncio~=0.24; extra == 'test'
Requires-Dist: pytest-httpx~=0.35; extra == 'test'
Requires-Dist: pytest~=8.0; extra == 'test'
Requires-Dist: ruff~=0.8; extra == 'test'
Requires-Dist: tox~=4.0; extra == 'test'
